<?xml version='1.0' encoding='utf-8'?>
<annotation><filename>frame_444.jpg</filename><object><name>person</name><bndbox><xmin>1102.231375475858</xmin><ymin>337.65325061813815</ymin><xmax>3323.4526820693127</xmax><ymax>2475.138596042485</ymax></bndbox></object><object><name>person</name><bndbox><xmin>2.407398262107563</xmin><ymin>1211.9805772774191</ymin><xmax>1154.7883740970847</xmax><ymax>3360.982553160694</ymax></bndbox></object><object><name>person</name><bndbox><xmin>2025.3240112250678</xmin><ymin>1207.4681483781537</ymin><xmax>4928.99780642654</xmax><ymax>3353.4572604373675</ymax></bndbox></object><object><name>person</name><bndbox><xmin>2725.26466456804</xmin><ymin>1339.3410049385752</ymin><xmax>6557.286279749818</xmax><ymax>3482.2312531400135</ymax></bndbox></object></annotation>