<?xml version='1.0' encoding='utf-8'?>
<annotation><filename>frame_354.jpg</filename><object><name>person</name><bndbox><xmin>1148.0822280440734</xmin><ymin>307.3477282582696</ymin><xmax>3505.439624659928</xmax><ymax>2441.594576350024</ymax></bndbox></object><object><name>person</name><bndbox><xmin>-13.94925821276604</xmin><ymin>1206.754372144383</ymin><xmax>1204.855160123525</xmax><ymax>3352.768753551543</ymax></bndbox></object><object><name>person</name><bndbox><xmin>2170.3761026226703</xmin><ymin>1196.2500174749327</ymin><xmax>5412.190802216699</xmax><ymax>3340.5635649976502</ymax></bndbox></object><object><name>person</name><bndbox><xmin>3106.50196769135</xmin><ymin>1150.0308697001096</ymin><xmax>6942.058259943458</xmax><ymax>3300.667496790897</ymax></bndbox></object></annotation>