<?xml version='1.0' encoding='utf-8'?>
<annotation><filename>frame_188.jpg</filename><object><name>person</name><bndbox><xmin>1748.9970776608586</xmin><ymin>277.49417330311394</ymin><xmax>4622.974850136637</xmax><ymax>2414.4901464311033</ymax></bndbox></object><object><name>person</name><bndbox><xmin>819.4348097180334</xmin><ymin>1112.930312209535</ymin><xmax>2972.0009446487566</xmax><ymax>3259.9476467561026</ymax></bndbox></object><object><name>person</name><bndbox><xmin>3307.029605992773</xmin><ymin>1013.6525453404456</ymin><xmax>7141.709804252285</xmax><ymax>3158.9411445764736</ymax></bndbox></object><object><name>person</name><bndbox><xmin>-24.830764492586923</xmin><ymin>1466.0385244859303</ymin><xmax>1081.6470925966435</xmax><ymax>3620.988301400949</ymax></bndbox></object></annotation>