<?xml version='1.0' encoding='utf-8'?>
<annotation><filename>frame_55.jpg</filename><object><name>person</name><bndbox><xmin>1675.0937956197884</xmin><ymin>269.17751760403553</ymin><xmax>4662.7552587252885</xmax><ymax>2407.951028195118</ymax></bndbox></object><object><name>person</name><bndbox><xmin>1076.7528169532886</xmin><ymin>1161.2523477205793</ymin><xmax>3465.075655600175</xmax><ymax>3307.2085673624115</ymax></bndbox></object><object><name>person</name><bndbox><xmin>3313.7846272130414</xmin><ymin>1207.8285841614086</ymin><xmax>7150.0697009358755</xmax><ymax>3355.8054544944025</ymax></bndbox></object><object><name>person</name><bndbox><xmin>579.4609272697685</xmin><ymin>1559.5505094467012</ymin><xmax>2274.2148923310756</xmax><ymax>3711.3234066316713</ymax></bndbox></object></annotation>