<?xml version='1.0' encoding='utf-8'?>
<annotation><filename>frame_205.jpg</filename><object><name>person</name><bndbox><xmin>1697.9909357026893</xmin><ymin>254.5764443361254</ymin><xmax>4534.399314562981</xmax><ymax>2392.2073917284033</ymax></bndbox></object><object><name>person</name><bndbox><xmin>737.5354444239504</xmin><ymin>1058.0143794002593</ymin><xmax>2814.295130460213</xmax><ymax>3203.3650036575623</ymax></bndbox></object><object><name>person</name><bndbox><xmin>3248.385953073762</xmin><ymin>1046.1545657864233</ymin><xmax>7091.877515786316</xmax><ymax>3196.40855165791</ymax></bndbox></object><object><name>person</name><bndbox><xmin>-10.293579487855766</xmin><ymin>1502.03996728379</ymin><xmax>969.8541636815928</xmax><ymax>3661.1633364308045</ymax></bndbox></object></annotation>